encryption/__init__.py
encryption/admin.py
encryption/apps.py
encryption/models.py
encryption/tests.py
encryption/views.py
mysite/__init__.py
mysite/asgi.py
mysite/cli.py
mysite/settings.py
mysite/urls.py
mysite/wsgi.py
unique_project_test_behmah-1.0.dist-info/METADATA
unique_project_test_behmah-1.0.dist-info/WHEEL
unique_project_test_behmah-1.0.dist-info/entry_points.txt
unique_project_test_behmah-1.0.dist-info/top_level.txt
unique_project_test_behmah-1.0.dist-info/RECORD
