Metadata-Version: 2.1
Name: unique_project_test_behmah
Version: 1.0
Requires-Python: <3.13,>=3.12
Requires-Dist: alabaster ==1.0.0
Requires-Dist: asgiref ==3.8.1
Requires-Dist: babel ==2.16.0
Requires-Dist: certifi ==2024.8.30
Requires-Dist: charset-normalizer ==3.3.2
Requires-Dist: Django ==5.1.1
Requires-Dist: docutils ==0.21.2
Requires-Dist: idna ==3.9
Requires-Dist: imagesize ==1.4.1
Requires-Dist: Jinja2 ==3.1.4
Requires-Dist: MarkupSafe ==2.1.5
Requires-Dist: packaging ==24.1
Requires-Dist: Pygments ==2.18.0
Requires-Dist: requests ==2.32.3
Requires-Dist: snowballstemmer ==2.2.0
Requires-Dist: Sphinx ==8.0.2
Requires-Dist: sphinxcontrib-applehelp ==2.0.0
Requires-Dist: sphinxcontrib-devhelp ==2.0.0
Requires-Dist: sphinxcontrib-htmlhelp ==2.1.0
Requires-Dist: sphinxcontrib-jsmath ==1.0.1
Requires-Dist: sphinxcontrib-qthelp ==2.0.0
Requires-Dist: sphinxcontrib-serializinghtml ==2.0.0
Requires-Dist: sqlparse ==0.5.1
Requires-Dist: urllib3 ==2.2.3
